{"raceID":"20221108NY36597","resultsType":"live","eevp":30.51,"statePostal":"NY","stateName":"New York","reportingunitID":"33","reportingunitLevel":1,"pollClosingTime":"2022-11-09T02:00:00.000Z","level":"state","electTotal":0,"lastUpdated":"2022-11-09T03:05:12.999Z","precinctsReporting":198,"precinctsTotal":688,"precinctsReportingPct":28.78,"candidates":[{"candidateID":"86379","voteCount":46923,"votePct":53.6,"colorIndex":0},{"candidateID":"86377","voteCount":40626,"votePct":46.4}],"parameters":{"vote":{"expected":{"actual":286988,"eevpCap":99},"total":87549,"registered":1142293},"precinctsReportingActual":198,"precinctsReportingProportional":196}}