{"raceID":"20221108MI24627","resultsType":"live","eevp":63.69,"statePostal":"MI","stateName":"Michigan","reportingunitID":"23","reportingunitLevel":1,"pollClosingTime":"2022-11-09T01:00:00.000Z","level":"state","electTotal":0,"lastUpdated":"2022-11-09T06:54:28.972Z","precinctsReporting":2669,"precinctsTotal":4690,"precinctsReportingPct":56.91,"candidates":[{"candidateID":"38021","voteCount":1629484,"votePct":53.3,"colorIndex":0},{"candidateID":"38020","voteCount":1427867,"votePct":46.7,"colorIndex":1}],"parameters":{"vote":{"expected":{"actual":4800000,"eevpCap":99},"total":3057351,"registered":8210166},"precinctsReportingActual":2669,"precinctsReportingProportional":2987}}