{"raceID":"20221108CO7749","resultsType":"live","eevp":90.04,"statePostal":"CO","stateName":"Colorado","reportingunitID":"6","reportingunitLevel":1,"pollClosingTime":"2022-11-09T02:00:00.000Z","level":"state","electTotal":0,"lastUpdated":"2022-11-11T00:53:48.837Z","precinctsReporting":2132,"precinctsTotal":3267,"precinctsReportingPct":65.26,"candidates":[{"candidateID":"14134","voteCount":1126523,"votePct":52.14,"colorIndex":1},{"candidateID":"14135","voteCount":1033894,"votePct":47.86,"colorIndex":0}],"parameters":{"vote":{"expected":{"actual":2399520,"eevpCap":99},"total":2160417,"registered":4316424},"precinctsReportingActual":2132,"precinctsReportingProportional":2941}}