{"raceID":"20221108IL16413","resultsType":"live","eevp":77.07,"statePostal":"IL","stateName":"Illinois","reportingunitID":"14","reportingunitLevel":1,"pollClosingTime":"2022-11-09T01:00:00.000Z","level":"state","electTotal":0,"lastUpdated":"2022-11-09T05:16:30.058Z","precinctsReporting":7964,"precinctsTotal":8910,"precinctsReportingPct":89.38,"candidates":[{"candidateID":"27492","voteCount":2061692,"votePct":56.92,"winner":"X","calledAt":"2022-11-09T01:00:04.280Z","colorIndex":0},{"candidateID":"29193","voteCount":1497712,"votePct":41.35,"colorIndex":1},{"candidateID":"29587","voteCount":62753,"votePct":1.73}],"parameters":{"vote":{"expected":{"actual":4700000,"eevpCap":99},"total":3622157,"registered":8800708},"precinctsReportingActual":7964,"precinctsReportingProportional":6867}}