{"raceID":"20221108TN43440","resultsType":"live","eevp":40.72,"statePostal":"TN","stateName":"Tennessee","reportingunitID":"43","reportingunitLevel":1,"pollClosingTime":"2022-11-09T01:00:00.000Z","level":"state","electTotal":0,"lastUpdated":"2022-11-09T02:34:16.055Z","precinctsReporting":225,"precinctsTotal":1853,"precinctsReportingPct":12.14,"candidates":[{"candidateID":"49923","voteCount":650805,"votePct":66.59,"winner":"X","calledAt":"2022-11-09T01:02:40.329Z","colorIndex":0},{"candidateID":"50748","voteCount":306190,"votePct":31.33,"colorIndex":1},{"candidateID":"50947","voteCount":8134,"votePct":0.83},{"candidateID":"50946","voteCount":5493,"votePct":0.56},{"candidateID":"50943","voteCount":1982,"votePct":0.2},{"candidateID":"50945","voteCount":1554,"votePct":0.16},{"candidateID":"50948","voteCount":1120,"votePct":0.11},{"candidateID":"50942","voteCount":838,"votePct":0.09},{"candidateID":"50949","voteCount":693,"votePct":0.07},{"candidateID":"50944","voteCount":478,"votePct":0.05}],"parameters":{"vote":{"expected":{"actual":2400000,"eevpCap":99},"total":977287,"registered":4426725},"precinctsReportingActual":225,"precinctsReportingProportional":755}}