{"raceID":"20221108OH37571","resultsType":"live","eevp":0,"statePostal":"OH","stateName":"Ohio","reportingunitID":"36","reportingunitLevel":1,"pollClosingTime":"2022-11-09T00:30:00.000Z","level":"state","electTotal":0,"lastUpdated":"2022-11-09T00:32:00.393Z","precinctsReporting":0,"precinctsTotal":570,"precinctsReportingPct":0,"candidates":[{"candidateID":"46095","voteCount":0,"votePct":0},{"candidateID":"47428","voteCount":0,"votePct":0}],"parameters":{"vote":{"expected":{"actual":288492,"eevpCap":99},"total":0,"registered":954419},"precinctsReportingActual":0,"precinctsReportingProportional":0}}