{"eventID":"IL-20221108_Eday64","stateID":14,"raceType":"General","raceTypeID":"G","tabulationStatus":"Awaiting Poll Close","raceCallStatus":"Too Early to Call","officeID":"H","officeName":"U.S. House","national":true,"uncontested":true,"seatName":"District 7","seatNum":"7","parameters":{"vote":{"expected":{"actual":468033,"eevpCap":99},"total":0,"registered":738704}},"isUpdated":true,"raceID":"20221108IL15996","electionDate":"2022-11-08","statePostal":"IL","incumbentID":"25754","candidates":{"25754":{"first":"Danny","last":"Davis","incumbent":true,"party":"Dem","candidateID":"25754","ballotOrder":1,"polID":"59339","polNum":"16944","electWon":0}}}