{"raceID":"20221108NC35387","resultsType":"live","eevp":63.2,"statePostal":"NC","stateName":"North Carolina","reportingunitID":"34","reportingunitLevel":1,"pollClosingTime":"2022-11-09T00:30:00.000Z","level":"state","electTotal":0,"lastUpdated":"2022-11-09T01:59:46.495Z","precinctsReporting":51,"precinctsTotal":162,"precinctsReportingPct":31.48,"candidates":[{"candidateID":"45587","voteCount":142819,"votePct":71.34,"winner":"X","calledAt":"2022-11-09T01:01:46.095Z","colorIndex":0},{"candidateID":"45594","voteCount":57371,"votePct":28.66,"colorIndex":1}],"parameters":{"vote":{"expected":{"actual":316740,"eevpCap":99},"total":200190,"registered":838302},"precinctsReportingActual":51,"precinctsReportingProportional":102}}