{"53001":{"statePostal":"WA","reportingunitID":"53001","reportingunitLevel":2,"pollClosingTime":"2022-11-09T04:00:00.000Z","level":"FIPSCode","fipsCode":"53001","electTotal":0,"lastUpdated":"2022-11-22T19:36:16.138Z","precinctsReporting":9,"eevp":99,"precinctsTotal":9,"precinctsReportingPct":100,"candidates":[{"candidateID":"9768","voteCount":3005,"votePct":77.89},{"candidateID":"9767","voteCount":853,"votePct":22.11}],"parameters":{"vote":{"expected":{"actual":3897,"eevpCap":99},"total":3858,"registered":7794},"precinctsReportingActual":0,"precinctsReportingProportional":9}},"53003":{"statePostal":"WA","reportingunitID":"53003","reportingunitLevel":2,"pollClosingTime":"2022-11-09T04:00:00.000Z","level":"FIPSCode","fipsCode":"53003","electTotal":0,"lastUpdated":"2022-11-16T23:12:26.111Z","precinctsReporting":21,"eevp":99,"precinctsTotal":21,"precinctsReportingPct":100,"candidates":[{"candidateID":"9768","voteCount":5605,"votePct":65.32},{"candidateID":"9767","voteCount":2976,"votePct":34.68}],"parameters":{"vote":{"expected":{"actual":8668,"eevpCap":99},"total":8581,"registered":14804},"precinctsReportingActual":0,"precinctsReportingProportional":21}},"53005":{"statePostal":"WA","reportingunitID":"53005","reportingunitLevel":2,"pollClosingTime":"2022-11-09T04:00:00.000Z","level":"FIPSCode","fipsCode":"53005","electTotal":0,"lastUpdated":"2022-11-22T19:42:08.496Z","precinctsReporting":153,"eevp":98,"precinctsTotal":156,"precinctsReportingPct":98.08,"candidates":[{"candidateID":"9768","voteCount":47296,"votePct":68.18},{"candidateID":"9767","voteCount":22075,"votePct":31.82}],"parameters":{"vote":{"expected":{"actual":70787,"eevpCap":99},"total":69371,"registered":125048},"precinctsReportingActual":0,"precinctsReportingProportional":153}},"53007":{"statePostal":"WA","reportingunitID":"53007","reportingunitLevel":2,"pollClosingTime":"2022-11-09T04:00:00.000Z","level":"FIPSCode","fipsCode":"53007","electTotal":0,"lastUpdated":"2022-11-23T00:14:14.781Z","precinctsReporting":62,"eevp":99,"precinctsTotal":63,"precinctsReportingPct":98.41,"candidates":[{"candidateID":"9768","voteCount":19912,"votePct":63.37},{"candidateID":"9767","voteCount":11512,"votePct":36.63}],"parameters":{"vote":{"expected":{"actual":31488,"eevpCap":99},"total":31424,"registered":50589},"precinctsReportingActual":0,"precinctsReportingProportional":62}},"53009":{"statePostal":"WA","reportingunitID":"53009","reportingunitLevel":2,"pollClosingTime":"2022-11-09T04:00:00.000Z","level":"FIPSCode","fipsCode":"53009","electTotal":0,"lastUpdated":"2022-11-23T00:14:15.050Z","precinctsReporting":71,"eevp":99,"precinctsTotal":72,"precinctsReportingPct":98.61,"candidates":[{"candidateID":"9768","voteCount":20560,"votePct":54.5},{"candidateID":"9767","voteCount":17162,"votePct":45.5}],"parameters":{"vote":{"expected":{"actual":37823,"eevpCap":99},"total":37722,"registered":56790},"precinctsReportingActual":0,"precinctsReportingProportional":71}},"53011":{"statePostal":"WA","reportingunitID":"53011","reportingunitLevel":2,"pollClosingTime":"2022-11-09T04:00:00.000Z","level":"FIPSCode","fipsCode":"53011","electTotal":0,"lastUpdated":"2022-11-22T19:42:31.114Z","precinctsReporting":401,"eevp":99,"precinctsTotal":405,"precinctsReportingPct":99.01,"candidates":[{"candidateID":"9768","voteCount":107197,"votePct":55.91},{"candidateID":"9767","voteCount":84526,"votePct":44.09}],"parameters":{"vote":{"expected":{"actual":193660,"eevpCap":99},"total":191723,"registered":323858},"precinctsReportingActual":0,"precinctsReportingProportional":401}},"53013":{"statePostal":"WA","reportingunitID":"53013","reportingunitLevel":2,"pollClosingTime":"2022-11-09T04:00:00.000Z","level":"FIPSCode","fipsCode":"53013","electTotal":0,"lastUpdated":"2022-11-16T00:00:50.029Z","precinctsReporting":3,"eevp":99,"precinctsTotal":3,"precinctsReportingPct":100,"candidates":[{"candidateID":"9768","voteCount":1501,"votePct":73.98},{"candidateID":"9767","voteCount":528,"votePct":26.02}],"parameters":{"vote":{"expected":{"actual":2049,"eevpCap":99},"total":2029,"registered":2833},"precinctsReportingActual":0,"precinctsReportingProportional":3}},"53015":{"statePostal":"WA","reportingunitID":"53015","reportingunitLevel":2,"pollClosingTime":"2022-11-09T04:00:00.000Z","level":"FIPSCode","fipsCode":"53015","electTotal":0,"lastUpdated":"2022-11-22T23:43:25.863Z","precinctsReporting":89,"eevp":99,"precinctsTotal":90,"precinctsReportingPct":98.89,"candidates":[{"candidateID":"9768","voteCount":28543,"votePct":66.79},{"candidateID":"9767","voteCount":14194,"votePct":33.21}],"parameters":{"vote":{"expected":{"actual":42834,"eevpCap":99},"total":42737,"registered":71073},"precinctsReportingActual":0,"precinctsReportingProportional":89}},"53017":{"statePostal":"WA","reportingunitID":"53017","reportingunitLevel":2,"pollClosingTime":"2022-11-09T04:00:00.000Z","level":"FIPSCode","fipsCode":"53017","electTotal":0,"lastUpdated":"2022-11-17T23:13:54.073Z","precinctsReporting":33,"eevp":99,"precinctsTotal":33,"precinctsReportingPct":100,"candidates":[{"candidateID":"9768","voteCount":11006,"votePct":71.97},{"candidateID":"9767","voteCount":4286,"votePct":28.03}],"parameters":{"vote":{"expected":{"actual":15446,"eevpCap":99},"total":15292,"registered":25872},"precinctsReportingActual":0,"precinctsReportingProportional":33}},"53019":{"statePostal":"WA","reportingunitID":"53019","reportingunitLevel":2,"pollClosingTime":"2022-11-09T04:00:00.000Z","level":"FIPSCode","fipsCode":"53019","electTotal":0,"lastUpdated":"2022-11-16T00:00:50.029Z","precinctsReporting":6,"eevp":99,"precinctsTotal":6,"precinctsReportingPct":100,"candidates":[{"candidateID":"9768","voteCount":2230,"votePct":72.85},{"candidateID":"9767","voteCount":831,"votePct":27.15}],"parameters":{"vote":{"expected":{"actual":3092,"eevpCap":99},"total":3061,"registered":5139},"precinctsReportingActual":0,"precinctsReportingProportional":6}},"53021":{"statePostal":"WA","reportingunitID":"53021","reportingunitLevel":2,"pollClosingTime":"2022-11-09T04:00:00.000Z","level":"FIPSCode","fipsCode":"53021","electTotal":0,"lastUpdated":"2022-11-16T00:00:50.029Z","precinctsReporting":53,"eevp":99,"precinctsTotal":54,"precinctsReportingPct":98.15,"candidates":[{"candidateID":"9768","voteCount":14383,"votePct":69.1},{"candidateID":"9767","voteCount":6431,"votePct":30.9}],"parameters":{"vote":{"expected":{"actual":21024,"eevpCap":99},"total":20814,"registered":42409},"precinctsReportingActual":0,"precinctsReportingProportional":53}},"53023":{"statePostal":"WA","reportingunitID":"53023","reportingunitLevel":2,"pollClosingTime":"2022-11-09T04:00:00.000Z","level":"FIPSCode","fipsCode":"53023","electTotal":0,"lastUpdated":"2022-11-22T01:24:24.574Z","precinctsReporting":3,"eevp":99,"precinctsTotal":3,"precinctsReportingPct":100,"candidates":[{"candidateID":"9768","voteCount":903,"votePct":74.2},{"candidateID":"9767","voteCount":314,"votePct":25.8}],"parameters":{"vote":{"expected":{"actual":1229,"eevpCap":99},"total":1217,"registered":1670},"precinctsReportingActual":0,"precinctsReportingProportional":3}},"53025":{"statePostal":"WA","reportingunitID":"53025","reportingunitLevel":2,"pollClosingTime":"2022-11-09T04:00:00.000Z","level":"FIPSCode","fipsCode":"53025","electTotal":0,"lastUpdated":"2022-11-22T01:20:47.810Z","precinctsReporting":59,"eevp":99,"precinctsTotal":60,"precinctsReportingPct":98.33,"candidates":[{"candidateID":"9768","voteCount":19234,"votePct":75.17},{"candidateID":"9767","voteCount":6353,"votePct":24.83}],"parameters":{"vote":{"expected":{"actual":25845,"eevpCap":99},"total":25587,"registered":47276},"precinctsReportingActual":0,"precinctsReportingProportional":59}},"53027":{"statePostal":"WA","reportingunitID":"53027","reportingunitLevel":2,"pollClosingTime":"2022-11-09T04:00:00.000Z","level":"FIPSCode","fipsCode":"53027","electTotal":0,"lastUpdated":"2022-11-22T23:14:36.449Z","precinctsReporting":59,"eevp":99,"precinctsTotal":60,"precinctsReportingPct":98.33,"candidates":[{"candidateID":"9768","voteCount":17710,"votePct":63.46},{"candidateID":"9767","voteCount":10199,"votePct":36.54}],"parameters":{"vote":{"expected":{"actual":28191,"eevpCap":99},"total":27909,"registered":47864},"precinctsReportingActual":0,"precinctsReportingProportional":59}},"53029":{"statePostal":"WA","reportingunitID":"53029","reportingunitLevel":2,"pollClosingTime":"2022-11-09T04:00:00.000Z","level":"FIPSCode","fipsCode":"53029","electTotal":0,"lastUpdated":"2022-11-16T00:11:51.229Z","precinctsReporting":74,"eevp":99,"precinctsTotal":75,"precinctsReportingPct":98.67,"candidates":[{"candidateID":"9768","voteCount":21461,"votePct":53.05},{"candidateID":"9767","voteCount":18995,"votePct":46.95}],"parameters":{"vote":{"expected":{"actual":40865,"eevpCap":99},"total":40456,"registered":60512},"precinctsReportingActual":0,"precinctsReportingProportional":74}},"53031":{"statePostal":"WA","reportingunitID":"53031","reportingunitLevel":2,"pollClosingTime":"2022-11-09T04:00:00.000Z","level":"FIPSCode","fipsCode":"53031","electTotal":0,"lastUpdated":"2022-11-22T01:24:38.586Z","precinctsReporting":33,"eevp":99,"precinctsTotal":33,"precinctsReportingPct":100,"candidates":[{"candidateID":"9767","voteCount":12189,"votePct":61.92},{"candidateID":"9768","voteCount":7495,"votePct":38.08}],"parameters":{"vote":{"expected":{"actual":19883,"eevpCap":99},"total":19684,"registered":27330},"precinctsReportingActual":0,"precinctsReportingProportional":33}},"53033":{"statePostal":"WA","reportingunitID":"53033","reportingunitLevel":2,"pollClosingTime":"2022-11-09T04:00:00.000Z","level":"FIPSCode","fipsCode":"53033","electTotal":0,"lastUpdated":"2022-11-22T23:43:27.510Z","precinctsReporting":1729,"eevp":99,"precinctsTotal":1746,"precinctsReportingPct":99.03,"candidates":[{"candidateID":"9767","voteCount":517394,"votePct":61.84},{"candidateID":"9768","voteCount":319221,"votePct":38.16}],"parameters":{"vote":{"expected":{"actual":839653,"eevpCap":99},"total":836615,"registered":1371193},"precinctsReportingActual":0,"precinctsReportingProportional":1729}},"53035":{"statePostal":"WA","reportingunitID":"53035","reportingunitLevel":2,"pollClosingTime":"2022-11-09T04:00:00.000Z","level":"FIPSCode","fipsCode":"53035","electTotal":0,"lastUpdated":"2022-11-23T00:22:47.067Z","precinctsReporting":229,"eevp":99,"precinctsTotal":231,"precinctsReportingPct":99.13,"candidates":[{"candidateID":"9768","voteCount":60405,"votePct":51.72},{"candidateID":"9767","voteCount":56382,"votePct":48.28}],"parameters":{"vote":{"expected":{"actual":117618,"eevpCap":99},"total":116787,"registered":184944},"precinctsReportingActual":0,"precinctsReportingProportional":229}},"53037":{"statePostal":"WA","reportingunitID":"53037","reportingunitLevel":2,"pollClosingTime":"2022-11-09T04:00:00.000Z","level":"FIPSCode","fipsCode":"53037","electTotal":0,"lastUpdated":"2022-11-22T19:43:44.900Z","precinctsReporting":35,"eevp":98,"precinctsTotal":36,"precinctsReportingPct":97.22,"candidates":[{"candidateID":"9768","voteCount":12253,"votePct":63.72},{"candidateID":"9767","voteCount":6976,"votePct":36.28}],"parameters":{"vote":{"expected":{"actual":19621,"eevpCap":99},"total":19229,"registered":29255},"precinctsReportingActual":0,"precinctsReportingProportional":35}},"53039":{"statePostal":"WA","reportingunitID":"53039","reportingunitLevel":2,"pollClosingTime":"2022-11-09T04:00:00.000Z","level":"FIPSCode","fipsCode":"53039","electTotal":0,"lastUpdated":"2022-11-18T15:31:26.331Z","precinctsReporting":21,"eevp":99,"precinctsTotal":21,"precinctsReportingPct":100,"candidates":[{"candidateID":"9768","voteCount":6647,"votePct":60.95},{"candidateID":"9767","voteCount":4258,"votePct":39.05}],"parameters":{"vote":{"expected":{"actual":11015,"eevpCap":99},"total":10905,"registered":15852},"precinctsReportingActual":0,"precinctsReportingProportional":21}},"53041":{"statePostal":"WA","reportingunitID":"53041","reportingunitLevel":2,"pollClosingTime":"2022-11-09T04:00:00.000Z","level":"FIPSCode","fipsCode":"53041","electTotal":0,"lastUpdated":"2022-11-23T00:29:18.056Z","precinctsReporting":68,"eevp":99,"precinctsTotal":69,"precinctsReportingPct":98.55,"candidates":[{"candidateID":"9768","voteCount":24549,"votePct":71.86},{"candidateID":"9767","voteCount":9611,"votePct":28.14}],"parameters":{"vote":{"expected":{"actual":34298,"eevpCap":99},"total":34160,"registered":54005},"precinctsReportingActual":0,"precinctsReportingProportional":68}},"53043":{"statePostal":"WA","reportingunitID":"53043","reportingunitLevel":2,"pollClosingTime":"2022-11-09T04:00:00.000Z","level":"FIPSCode","fipsCode":"53043","electTotal":0,"lastUpdated":"2022-11-16T23:50:19.340Z","precinctsReporting":9,"eevp":99,"precinctsTotal":9,"precinctsReportingPct":100,"candidates":[{"candidateID":"9768","voteCount":4498,"votePct":77.06},{"candidateID":"9767","voteCount":1339,"votePct":22.94}],"parameters":{"vote":{"expected":{"actual":5896,"eevpCap":99},"total":5837,"registered":8185},"precinctsReportingActual":0,"precinctsReportingProportional":9}},"53045":{"statePostal":"WA","reportingunitID":"53045","reportingunitLevel":2,"pollClosingTime":"2022-11-09T04:00:00.000Z","level":"FIPSCode","fipsCode":"53045","electTotal":0,"lastUpdated":"2022-11-16T00:00:50.029Z","precinctsReporting":53,"eevp":99,"precinctsTotal":54,"precinctsReportingPct":98.15,"candidates":[{"candidateID":"9768","voteCount":16842,"votePct":60.93},{"candidateID":"9767","voteCount":10801,"votePct":39.07}],"parameters":{"vote":{"expected":{"actual":27922,"eevpCap":99},"total":27643,"registered":43375},"precinctsReportingActual":0,"precinctsReportingProportional":53}},"53047":{"statePostal":"WA","reportingunitID":"53047","reportingunitLevel":2,"pollClosingTime":"2022-11-09T04:00:00.000Z","level":"FIPSCode","fipsCode":"53047","electTotal":0,"lastUpdated":"2022-11-22T19:44:16.980Z","precinctsReporting":31,"eevp":95,"precinctsTotal":33,"precinctsReportingPct":93.94,"candidates":[{"candidateID":"9768","voteCount":9704,"votePct":65.26},{"candidateID":"9767","voteCount":5166,"votePct":34.74}],"parameters":{"vote":{"expected":{"actual":15653,"eevpCap":99},"total":14870,"registered":25531},"precinctsReportingActual":0,"precinctsReportingProportional":31}},"53049":{"statePostal":"WA","reportingunitID":"53049","reportingunitLevel":2,"pollClosingTime":"2022-11-09T04:00:00.000Z","level":"FIPSCode","fipsCode":"53049","electTotal":0,"lastUpdated":"2022-11-16T00:00:50.029Z","precinctsReporting":21,"eevp":99,"precinctsTotal":21,"precinctsReportingPct":100,"candidates":[{"candidateID":"9768","voteCount":7010,"votePct":62.19},{"candidateID":"9767","voteCount":4262,"votePct":37.81}],"parameters":{"vote":{"expected":{"actual":11386,"eevpCap":99},"total":11272,"registered":16675},"precinctsReportingActual":0,"precinctsReportingProportional":21}},"53051":{"statePostal":"WA","reportingunitID":"53051","reportingunitLevel":2,"pollClosingTime":"2022-11-09T04:00:00.000Z","level":"FIPSCode","fipsCode":"53051","electTotal":0,"lastUpdated":"2022-11-22T01:25:02.310Z","precinctsReporting":12,"eevp":98.99,"precinctsTotal":12,"precinctsReportingPct":100,"candidates":[{"candidateID":"9768","voteCount":4513,"votePct":72.83},{"candidateID":"9767","voteCount":1684,"votePct":27.17}],"parameters":{"vote":{"expected":{"actual":6260,"eevpCap":99},"total":6197,"registered":10642},"precinctsReportingActual":0,"precinctsReportingProportional":12}},"53053":{"statePostal":"WA","reportingunitID":"53053","reportingunitLevel":2,"pollClosingTime":"2022-11-09T04:00:00.000Z","level":"FIPSCode","fipsCode":"53053","electTotal":0,"lastUpdated":"2022-11-21T20:37:31.267Z","precinctsReporting":683,"eevp":99,"precinctsTotal":690,"precinctsReportingPct":98.99,"candidates":[{"candidateID":"9768","voteCount":180938,"votePct":57.87},{"candidateID":"9767","voteCount":131726,"votePct":42.13}],"parameters":{"vote":{"expected":{"actual":315536,"eevpCap":99},"total":312664,"registered":545800},"precinctsReportingActual":0,"precinctsReportingProportional":683}},"53055":{"statePostal":"WA","reportingunitID":"53055","reportingunitLevel":2,"pollClosingTime":"2022-11-09T04:00:00.000Z","level":"FIPSCode","fipsCode":"53055","electTotal":0,"lastUpdated":"2022-11-16T00:00:50.029Z","precinctsReporting":18,"eevp":99,"precinctsTotal":18,"precinctsReportingPct":100,"candidates":[{"candidateID":"9767","voteCount":5970,"votePct":59.12},{"candidateID":"9768","voteCount":4128,"votePct":40.88}],"parameters":{"vote":{"expected":{"actual":10200,"eevpCap":99},"total":10098,"registered":14509},"precinctsReportingActual":0,"precinctsReportingProportional":18}},"53057":{"statePostal":"WA","reportingunitID":"53057","reportingunitLevel":2,"pollClosingTime":"2022-11-09T04:00:00.000Z","level":"FIPSCode","fipsCode":"53057","electTotal":0,"lastUpdated":"2022-11-22T19:44:55.759Z","precinctsReporting":103,"eevp":98,"precinctsTotal":105,"precinctsReportingPct":98.1,"candidates":[{"candidateID":"9768","voteCount":28776,"votePct":54.8},{"candidateID":"9767","voteCount":23738,"votePct":45.2}],"parameters":{"vote":{"expected":{"actual":53586,"eevpCap":99},"total":52514,"registered":84546},"precinctsReportingActual":0,"precinctsReportingProportional":103}},"53059":{"statePostal":"WA","reportingunitID":"53059","reportingunitLevel":2,"pollClosingTime":"2022-11-09T04:00:00.000Z","level":"FIPSCode","fipsCode":"53059","electTotal":0,"lastUpdated":"2022-11-22T19:46:39.581Z","precinctsReporting":12,"eevp":99,"precinctsTotal":12,"precinctsReportingPct":100,"candidates":[{"candidateID":"9768","voteCount":3680,"votePct":64.35},{"candidateID":"9767","voteCount":2039,"votePct":35.65}],"parameters":{"vote":{"expected":{"actual":5777,"eevpCap":99},"total":5719,"registered":9154},"precinctsReportingActual":0,"precinctsReportingProportional":12}},"53061":{"statePostal":"WA","reportingunitID":"53061","reportingunitLevel":2,"pollClosingTime":"2022-11-09T04:00:00.000Z","level":"FIPSCode","fipsCode":"53061","electTotal":0,"lastUpdated":"2022-11-22T01:08:46.125Z","precinctsReporting":627,"eevp":99,"precinctsTotal":633,"precinctsReportingPct":99.05,"candidates":[{"candidateID":"9768","voteCount":159877,"votePct":53.07},{"candidateID":"9767","voteCount":141403,"votePct":46.93}],"parameters":{"vote":{"expected":{"actual":303739,"eevpCap":99},"total":301280,"registered":505178},"precinctsReportingActual":0,"precinctsReportingProportional":627}},"53063":{"statePostal":"WA","reportingunitID":"53063","reportingunitLevel":2,"pollClosingTime":"2022-11-09T04:00:00.000Z","level":"FIPSCode","fipsCode":"53063","electTotal":0,"lastUpdated":"2022-11-18T15:37:52.755Z","precinctsReporting":443,"eevp":99,"precinctsTotal":447,"precinctsReportingPct":99.11,"candidates":[{"candidateID":"9768","voteCount":126748,"votePct":60.49},{"candidateID":"9767","voteCount":82774,"votePct":39.51}],"parameters":{"vote":{"expected":{"actual":211638,"eevpCap":99},"total":209522,"registered":357355},"precinctsReportingActual":0,"precinctsReportingProportional":443}},"53065":{"statePostal":"WA","reportingunitID":"53065","reportingunitLevel":2,"pollClosingTime":"2022-11-09T04:00:00.000Z","level":"FIPSCode","fipsCode":"53065","electTotal":0,"lastUpdated":"2022-11-22T22:37:14.172Z","precinctsReporting":41,"eevp":97,"precinctsTotal":42,"precinctsReportingPct":97.62,"candidates":[{"candidateID":"9768","voteCount":16149,"votePct":75.55},{"candidateID":"9767","voteCount":5226,"votePct":24.45}],"parameters":{"vote":{"expected":{"actual":22036,"eevpCap":99},"total":21375,"registered":34146},"precinctsReportingActual":0,"precinctsReportingProportional":41}},"53067":{"statePostal":"WA","reportingunitID":"53067","reportingunitLevel":2,"pollClosingTime":"2022-11-09T04:00:00.000Z","level":"FIPSCode","fipsCode":"53067","electTotal":0,"lastUpdated":"2022-11-22T19:45:37.646Z","precinctsReporting":236,"eevp":96,"precinctsTotal":246,"precinctsReportingPct":95.93,"candidates":[{"candidateID":"9767","voteCount":57410,"votePct":50.31},{"candidateID":"9768","voteCount":56710,"votePct":49.69}],"parameters":{"vote":{"expected":{"actual":118875,"eevpCap":99},"total":114120,"registered":194842},"precinctsReportingActual":0,"precinctsReportingProportional":236}},"53069":{"statePostal":"WA","reportingunitID":"53069","reportingunitLevel":2,"pollClosingTime":"2022-11-09T04:00:00.000Z","level":"FIPSCode","fipsCode":"53069","electTotal":0,"lastUpdated":"2022-11-18T15:38:53.343Z","precinctsReporting":3,"eevp":94.99,"precinctsTotal":3,"precinctsReportingPct":100,"candidates":[{"candidateID":"9768","voteCount":1597,"votePct":67.41},{"candidateID":"9767","voteCount":772,"votePct":32.59}],"parameters":{"vote":{"expected":{"actual":2494,"eevpCap":99},"total":2369,"registered":3453},"precinctsReportingActual":0,"precinctsReportingProportional":3}},"53071":{"statePostal":"WA","reportingunitID":"53071","reportingunitLevel":2,"pollClosingTime":"2022-11-09T04:00:00.000Z","level":"FIPSCode","fipsCode":"53071","electTotal":0,"lastUpdated":"2022-11-22T19:46:25.883Z","precinctsReporting":42,"eevp":93,"precinctsTotal":45,"precinctsReportingPct":93.33,"candidates":[{"candidateID":"9768","voteCount":13102,"votePct":60.91},{"candidateID":"9767","voteCount":8409,"votePct":39.09}],"parameters":{"vote":{"expected":{"actual":23130,"eevpCap":99},"total":21511,"registered":40190},"precinctsReportingActual":0,"precinctsReportingProportional":42}},"53073":{"statePostal":"WA","reportingunitID":"53073","reportingunitLevel":2,"pollClosingTime":"2022-11-09T04:00:00.000Z","level":"FIPSCode","fipsCode":"53073","electTotal":0,"lastUpdated":"2022-11-22T19:46:48.440Z","precinctsReporting":193,"eevp":99,"precinctsTotal":195,"precinctsReportingPct":98.97,"candidates":[{"candidateID":"9767","voteCount":52982,"votePct":50.66},{"candidateID":"9768","voteCount":51596,"votePct":49.34}],"parameters":{"vote":{"expected":{"actual":105634,"eevpCap":99},"total":104578,"registered":169705},"precinctsReportingActual":0,"precinctsReportingProportional":193}},"53075":{"statePostal":"WA","reportingunitID":"53075","reportingunitLevel":2,"pollClosingTime":"2022-11-09T04:00:00.000Z","level":"FIPSCode","fipsCode":"53075","electTotal":0,"lastUpdated":"2022-11-18T01:05:51.218Z","precinctsReporting":28,"eevp":92,"precinctsTotal":30,"precinctsReportingPct":93.33,"candidates":[{"candidateID":"9768","voteCount":7401,"votePct":53.88},{"candidateID":"9767","voteCount":6336,"votePct":46.12}],"parameters":{"vote":{"expected":{"actual":14932,"eevpCap":99},"total":13737,"registered":27885},"precinctsReportingActual":0,"precinctsReportingProportional":28}},"53077":{"statePostal":"WA","reportingunitID":"53077","reportingunitLevel":2,"pollClosingTime":"2022-11-09T04:00:00.000Z","level":"FIPSCode","fipsCode":"53077","electTotal":0,"lastUpdated":"2022-11-22T19:47:11.899Z","precinctsReporting":157,"eevp":99,"precinctsTotal":159,"precinctsReportingPct":98.74,"candidates":[{"candidateID":"9768","voteCount":40802,"votePct":67.89},{"candidateID":"9767","voteCount":19302,"votePct":32.11}],"parameters":{"vote":{"expected":{"actual":60711,"eevpCap":99},"total":60104,"registered":135287},"precinctsReportingActual":0,"precinctsReportingProportional":157}},"summary":{"raceID":"20221108WA49443","resultsType":"live","eevp":99,"statePostal":"WA","stateName":"Washington","reportingunitID":"48","reportingunitLevel":1,"pollClosingTime":"2022-11-09T04:00:00.000Z","level":"state","electTotal":0,"lastUpdated":"2022-11-23T00:29:18.057Z","precinctsReporting":5940,"precinctsTotal":6000,"precinctsReportingPct":99,"candidates":[{"candidateID":"9768","voteCount":1485187,"votePct":52.03,"winner":"X","calledAt":"2022-11-16T00:00:49.557Z","colorIndex":0},{"candidateID":"9767","voteCount":1369384,"votePct":47.97,"colorIndex":1}],"parameters":{"vote":{"expected":{"actual":2879769,"eevpCap":99},"total":2854571,"registered":4760301},"precinctsReportingActual":0,"precinctsReportingProportional":5940}}}