{"raceID":"20221108KS17355","resultsType":"live","eevp":95.73,"statePostal":"KS","stateName":"Kansas","reportingunitID":"17","reportingunitLevel":1,"pollClosingTime":"2022-11-09T01:00:00.000Z","level":"state","electTotal":0,"lastUpdated":"2022-11-09T05:45:28.531Z","precinctsReporting":1028,"precinctsTotal":1077,"precinctsReportingPct":95.45,"candidates":[{"candidateID":"7226","voteCount":126081,"votePct":57.4,"winner":"X","calledAt":"2022-11-09T04:55:06.182Z","colorIndex":0},{"candidateID":"7715","voteCount":93591,"votePct":42.6,"colorIndex":1}],"parameters":{"vote":{"expected":{"actual":229474,"eevpCap":99},"total":219672,"registered":712222},"precinctsReportingActual":1028,"precinctsReportingProportional":1031}}