{"raceID":"20221108IL16005","resultsType":"live","eevp":15.31,"statePostal":"IL","stateName":"Illinois","reportingunitID":"14","reportingunitLevel":1,"pollClosingTime":"2022-11-09T01:00:00.000Z","level":"state","electTotal":0,"lastUpdated":"2022-11-09T03:15:07.656Z","precinctsReporting":100,"precinctsTotal":683,"precinctsReportingPct":14.64,"candidates":[{"candidateID":"29292","voteCount":28552,"votePct":63.2,"colorIndex":0},{"candidateID":"29593","voteCount":16628,"votePct":36.8,"colorIndex":1}],"parameters":{"vote":{"expected":{"actual":295147,"eevpCap":99},"total":45180,"registered":1244778},"precinctsReportingActual":100,"precinctsReportingProportional":105}}