{"summary":{"raceID":"20221108CA5713","resultsType":"live","eevp":99,"statePostal":"CA","stateName":"California","reportingunitID":"5","reportingunitLevel":1,"pollClosingTime":"2022-11-09T04:00:00.000Z","level":"state","electTotal":0,"lastUpdated":"2022-12-06T14:00:15.708Z","precinctsReporting":1550,"precinctsTotal":1566,"precinctsReportingPct":98.98,"candidates":[{"candidateID":"22968","voteCount":103058,"votePct":61.01,"winner":"X","calledAt":"2022-11-10T17:55:34.033Z","colorIndex":1},{"candidateID":"22970","voteCount":65849,"votePct":38.99}],"parameters":{"vote":{"expected":{"actual":169830,"eevpCap":99},"total":168907,"registered":2538274},"precinctsReportingActual":1566,"precinctsReportingProportional":1550}},"06071":{"statePostal":"CA","reportingunitID":"6071","reportingunitLevel":2,"pollClosingTime":"2022-11-09T04:00:00.000Z","level":"FIPSCode","fipsCode":"06071","electTotal":0,"lastUpdated":"2022-12-06T14:00:15.708Z","precinctsReporting":1520,"eevp":99,"precinctsTotal":1535,"precinctsReportingPct":99.02,"candidates":[{"candidateID":"22968","voteCount":99224,"votePct":61.14},{"candidateID":"22970","voteCount":63078,"votePct":38.86}],"parameters":{"vote":{"expected":{"actual":163163,"eevpCap":99},"total":162302,"registered":383719},"precinctsReportingActual":1535,"precinctsReportingProportional":1520}},"06029":{"statePostal":"CA","reportingunitID":"6029","reportingunitLevel":2,"pollClosingTime":"2022-11-09T04:00:00.000Z","level":"FIPSCode","fipsCode":"06029","electTotal":0,"lastUpdated":"2022-12-05T16:28:26.854Z","precinctsReporting":21,"eevp":99,"precinctsTotal":21,"precinctsReportingPct":100,"candidates":[{"candidateID":"22968","voteCount":2313,"votePct":61.19},{"candidateID":"22970","voteCount":1467,"votePct":38.81}],"parameters":{"vote":{"expected":{"actual":3818,"eevpCap":99},"total":3780,"registered":8930},"precinctsReportingActual":21,"precinctsReportingProportional":21}},"06037":{"statePostal":"CA","reportingunitID":"6037","reportingunitLevel":2,"pollClosingTime":"2022-11-09T04:00:00.000Z","level":"FIPSCode","fipsCode":"06037","electTotal":0,"lastUpdated":"2022-12-05T14:15:10.161Z","precinctsReporting":10,"eevp":99,"precinctsTotal":10,"precinctsReportingPct":100,"candidates":[{"candidateID":"22968","voteCount":1521,"votePct":53.84},{"candidateID":"22970","voteCount":1304,"votePct":46.16}],"parameters":{"vote":{"expected":{"actual":2849,"eevpCap":99},"total":2825,"registered":8432},"precinctsReportingActual":10,"precinctsReportingProportional":10}}}