{"raceID":"20221108MT28576","resultsType":"live","eevp":11.88,"statePostal":"MT","stateName":"Montana","reportingunitID":"27","reportingunitLevel":1,"pollClosingTime":"2022-11-09T03:00:00.000Z","level":"state","electTotal":0,"lastUpdated":"2022-11-09T04:03:30.401Z","precinctsReporting":34,"precinctsTotal":362,"precinctsReportingPct":9.39,"candidates":[{"candidateID":"36217","voteCount":12202,"votePct":42.2,"colorIndex":0},{"candidateID":"36218","voteCount":9475,"votePct":32.77,"colorIndex":1},{"candidateID":"36216","voteCount":6828,"votePct":23.61},{"candidateID":"36002","voteCount":411,"votePct":1.42}],"parameters":{"vote":{"expected":{"actual":243334,"eevpCap":99},"total":28916,"registered":497392},"precinctsReportingActual":34,"precinctsReportingProportional":43}}